{
   "abstract" : "Insert POD from Rinci metadata",
   "author" : [
      "Steven Haryanto <stevenharyanto@gmail.com>"
   ],
   "dynamic_config" : 0,
   "generated_by" : "Dist::Zilla version 4.300015, CPAN::Meta::Converter version 2.120921",
   "license" : [
      "perl_5"
   ],
   "meta-spec" : {
      "url" : "http://search.cpan.org/perldoc?CPAN::Meta::Spec",
      "version" : "2"
   },
   "name" : "Pod-Weaver-Plugin-Perinci",
   "prereqs" : {
      "build" : {
         "requires" : {
            "Module::Build" : "0.3601"
         }
      },
      "configure" : {
         "requires" : {
            "Module::Build" : "0.3601"
         }
      },
      "develop" : {
         "requires" : {
            "Test::Rinci" : "0.01"
         }
      },
      "runtime" : {
         "requires" : {
            "Log::Any" : "0",
            "Perinci::To::POD" : "0",
            "Pod::Weaver" : "0",
            "perl" : "5.010000"
         }
      }
   },
   "release_status" : "stable",
   "resources" : {
      "homepage" : "http://search.cpan.org/dist/Pod-Weaver-Plugin-Perinci/",
      "repository" : {
         "url" : "http://github.com/sharyanto/perl-Pod-Weaver-Plugin-Perinci"
      }
   },
   "version" : "0.09"
}

